sphinx_asciidoc/__init__.py
sphinx_asciidoc/builder.py
sphinx_asciidoc/writer.py
sphinx_asciidoc-1.0.2.dist-info/DESCRIPTION.rst
sphinx_asciidoc-1.0.2.dist-info/METADATA
sphinx_asciidoc-1.0.2.dist-info/RECORD
sphinx_asciidoc-1.0.2.dist-info/WHEEL
sphinx_asciidoc-1.0.2.dist-info/entry_points.txt
sphinx_asciidoc-1.0.2.dist-info/metadata.json
sphinx_asciidoc-1.0.2.dist-info/top_level.txt
