Metadata-Version: 2.0
Name: sphinx-asciidoc
Version: 1.0.2
Summary: A custom Sphinx builder to make asciidoc output
Home-page: https://github.com/lruzicka/sphinx-asciidoc
Author: Lukáš Růžička
Author-email: lukas.ruzicka@gmail.com
License: UNKNOWN
Keywords: sphinx extension builder asciidoc
Platform: UNKNOWN
Classifier: Development Status :: 4 - Beta
Classifier: Intended Audience :: Developers
Classifier: Topic :: Software Development :: Build Tools
Classifier: License :: OSI Approved :: BSD License
Classifier: Programming Language :: Python :: 2.7
Classifier: Programming Language :: Python :: 3
Requires-Dist: sphinx
